[
  {
    "artistId": 1,
    "surname": "Lucas",
    "name": "George",
    "DOB": "1944-01-01T00:00:00.000Z"
  },
  {
    "artistId": 2,
    "surname": "Hamill",
    "name": "Mark",
    "DOB": "1951-01-01T00:00:00.000Z"
  },
  {
    "artistId": 3,
    "surname": "Ford",
    "name": "Harrison",
    "DOB": "1942-01-01T00:00:00.000Z"
  },
  {
    "artistId": 4,
    "surname": "Fisher",
    "name": "Carrie",
    "DOB": "1956-01-01T00:00:00.000Z"
  },
  {
    "artistId": 5,
    "surname": "Cushing",
    "name": "Peter",
    "DOB": "1913-01-01T00:00:00.000Z"
  },
  {
    "artistId": 6,
    "surname": "Daniels",
    "name": "Anthony",
    "DOB": "1946-01-01T00:00:00.000Z"
  },
  {
    "artistId": 31,
    "surname": "Hanks",
    "name": "Tom",
    "DOB": "1956-01-01T00:00:00.000Z"
  },
  {
    "artistId": 32,
    "surname": "Wright",
    "name": "Robin",
    "DOB": "1966-01-01T00:00:00.000Z"
  },
  {
    "artistId": 39,
    "surname": "Mendes",
    "name": "Sam",
    "DOB": "1965-01-01T00:00:00.000Z"
  },
  {
    "artistId": 40,
    "surname": "Welles",
    "name": "Orson",
    "DOB": "1915-01-01T00:00:00.000Z"
  },
  {
    "artistId": 42,
    "surname": "von Trier",
    "name": "Lars",
    "DOB": "1956-01-01T00:00:00.000Z"
  },
  {
    "artistId": 48,
    "surname": "Bean",
    "name": "Sean",
    "DOB": "1959-01-01T00:00:00.000Z"
  },
  {
    "artistId": 49,
    "surname": "Bello",
    "name": "Maria",
    "DOB": "1967-01-01T00:00:00.000Z"
  },
  {
    "artistId": 50,
    "surname": "Deneuve",
    "name": "Catherine",
    "DOB": "1943-01-01T00:00:00.000Z"
  },
  {
    "artistId": 53,
    "surname": "Stormare",
    "name": "Peter",
    "DOB": "1953-01-01T00:00:00.000Z"
  },
  {
    "artistId": 59,
    "surname": "Besson",
    "name": "Luc",
    "DOB": "1959-01-01T00:00:00.000Z"
  },
  {
    "artistId": 62,
    "surname": "Willis",
    "name": "Bruce",
    "DOB": "1955-01-01T00:00:00.000Z"
  },
  {
    "artistId": 64,
    "surname": "Oldman",
    "name": "Gary",
    "DOB": "1958-01-01T00:00:00.000Z"
  },
  {
    "artistId": 65,
    "surname": "Holm",
    "name": "Ian",
    "DOB": "1931-01-01T00:00:00.000Z"
  },
  {
    "artistId": 66,
    "surname": "Tucker",
    "name": "Chris",
    "DOB": "1971-01-01T00:00:00.000Z"
  },
  {
    "artistId": 68,
    "surname": "Lang",
    "name": "Fritz",
    "DOB": "1890-01-01T00:00:00.000Z"
  },
  {
    "artistId": 85,
    "surname": "Depp",
    "name": "Johnny",
    "DOB": "1963-01-01T00:00:00.000Z"
  },
  {
    "artistId": 99,
    "surname": "Plummer",
    "name": "Amanda",
    "DOB": "1957-01-01T00:00:00.000Z"
  },
  {
    "artistId": 103,
    "surname": "Ruffalo",
    "name": "Mark",
    "DOB": "1967-01-01T00:00:00.000Z"
  },
  {
    "artistId": 108,
    "surname": "Jackson",
    "name": "Peter",
    "DOB": "1961-01-01T00:00:00.000Z"
  },
  {
    "artistId": 109,
    "surname": "Wood",
    "name": "Elijah",
    "DOB": "1981-01-01T00:00:00.000Z"
  },
  {
    "artistId": 110,
    "surname": "Mortensen",
    "name": "Viggo",
    "DOB": "1958-01-01T00:00:00.000Z"
  },
  {
    "artistId": 112,
    "surname": "Blanchett",
    "name": "Cate",
    "DOB": "1969-01-01T00:00:00.000Z"
  },
  {
    "artistId": 113,
    "surname": "Lee",
    "name": "Christopher",
    "DOB": "1922-01-01T00:00:00.000Z"
  },
  {
    "artistId": 114,
    "surname": "Bloom",
    "name": "Orlando",
    "DOB": "1977-01-01T00:00:00.000Z"
  },
  {
    "artistId": 130,
    "surname": "Baker",
    "name": "Kenny",
    "DOB": "1934-01-01T00:00:00.000Z"
  },
  {
    "artistId": 131,
    "surname": "Gyllenhaal",
    "name": "Jake",
    "DOB": "1980-01-01T00:00:00.000Z"
  },
  {
    "artistId": 134,
    "surname": "Foxx",
    "name": "Jamie",
    "DOB": "1967-01-01T00:00:00.000Z"
  },
  {
    "artistId": 138,
    "surname": "Tarantino",
    "name": "Quentin",
    "DOB": "1963-01-01T00:00:00.000Z"
  },
  {
    "artistId": 139,
    "surname": "Thurman",
    "name": "Uma",
    "DOB": "1970-01-01T00:00:00.000Z"
  },
  {
    "artistId": 140,
    "surname": "Liu",
    "name": "Lucy",
    "DOB": "1968-01-01T00:00:00.000Z"
  },
  {
    "artistId": 141,
    "surname": "Carradine",
    "name": "David",
    "DOB": "1936-01-01T00:00:00.000Z"
  },
  {
    "artistId": 147,
    "surname": "Madsen",
    "name": "Michael",
    "DOB": "1957-01-01T00:00:00.000Z"
  },
  {
    "artistId": 190,
    "surname": "Eastwood",
    "name": "Clint",
    "DOB": "1930-01-01T00:00:00.000Z"
  },
  {
    "artistId": 192,
    "surname": "Freeman",
    "name": "Morgan",
    "DOB": "1937-01-01T00:00:00.000Z"
  },
  {
    "artistId": 193,
    "surname": "Hackman",
    "name": "Gene",
    "DOB": "1930-01-01T00:00:00.000Z"
  },
  {
    "artistId": 194,
    "surname": "Harris",
    "name": "Richard",
    "DOB": "1930-01-01T00:00:00.000Z"
  },
  {
    "artistId": 201,
    "surname": "Gondry",
    "name": "Michel",
    "DOB": "1963-01-01T00:00:00.000Z"
  },
  {
    "artistId": 204,
    "surname": "Winslet",
    "name": "Kate",
    "DOB": "1975-01-01T00:00:00.000Z"
  },
  {
    "artistId": 205,
    "surname": "Dunst",
    "name": "Kirsten",
    "DOB": "1982-01-01T00:00:00.000Z"
  },
  {
    "artistId": 206,
    "surname": "Carrey",
    "name": "Jim",
    "DOB": "1962-01-01T00:00:00.000Z"
  },
  {
    "artistId": 207,
    "surname": "Wilkinson",
    "name": "Tom",
    "DOB": "1948-01-01T00:00:00.000Z"
  },
  {
    "artistId": 223,
    "surname": "González Iñárritu",
    "name": "Alejandro",
    "DOB": "1963-01-01T00:00:00.000Z"
  },
  {
    "artistId": 224,
    "surname": "Cronenberg",
    "name": "David",
    "DOB": "1943-01-01T00:00:00.000Z"
  },
  {
    "artistId": 225,
    "surname": "Holmes",
    "name": "Ashton",
    "DOB": "1978-01-01T00:00:00.000Z"
  },
  {
    "artistId": 227,
    "surname": "Hurt",
    "name": "William",
    "DOB": "1950-01-01T00:00:00.000Z"
  },
  {
    "artistId": 228,
    "surname": "Harris",
    "name": "Ed",
    "DOB": "1950-01-01T00:00:00.000Z"
  },
  {
    "artistId": 240,
    "surname": "Kubrick",
    "name": "Stanley",
    "DOB": "1928-01-01T00:00:00.000Z"
  },
  {
    "artistId": 245,
    "surname": "Dullea",
    "name": "Keir",
    "DOB": "1936-01-01T00:00:00.000Z"
  },
  {
    "artistId": 246,
    "surname": "Lockwood",
    "name": "Gary",
    "DOB": "1937-01-01T00:00:00.000Z"
  },
  {
    "artistId": 247,
    "surname": "Sylvester",
    "name": "William",
    "DOB": "1922-01-01T00:00:00.000Z"
  },
  {
    "artistId": 248,
    "surname": "Richter",
    "name": "Daniel",
    "DOB": "1939-01-01T00:00:00.000Z"
  },
  {
    "artistId": 253,
    "surname": "Rain",
    "name": "Douglas",
    "DOB": "1928-01-01T00:00:00.000Z"
  },
  {
    "artistId": 258,
    "surname": "García Bernal",
    "name": "Gael",
    "DOB": "1978-01-01T00:00:00.000Z"
  },
  {
    "artistId": 270,
    "surname": "Barraza",
    "name": "Adriana",
    "DOB": "1956-01-01T00:00:00.000Z"
  },
  {
    "artistId": 287,
    "surname": "Pitt",
    "name": "Brad",
    "DOB": "1963-01-01T00:00:00.000Z"
  },
  {
    "artistId": 289,
    "surname": "Stowe",
    "name": "Madeleine",
    "DOB": "1958-01-01T00:00:00.000Z"
  },
  {
    "artistId": 290,
    "surname": "Plummer",
    "name": "Christopher",
    "DOB": "1929-01-01T00:00:00.000Z"
  },
  {
    "artistId": 335,
    "surname": "Shannon",
    "name": "Michael",
    "DOB": "1974-01-01T00:00:00.000Z"
  },
  {
    "artistId": 349,
    "surname": "Glenn",
    "name": "Scott",
    "DOB": "1939-01-01T00:00:00.000Z"
  },
  {
    "artistId": 351,
    "surname": "Davis",
    "name": "Judy",
    "DOB": "1955-01-01T00:00:00.000Z"
  },
  {
    "artistId": 368,
    "surname": "Witherspoon",
    "name": "Reese",
    "DOB": "1976-01-01T00:00:00.000Z"
  },
  {
    "artistId": 380,
    "surname": "De Niro",
    "name": "Robert",
    "DOB": "1943-01-01T00:00:00.000Z"
  },
  {
    "artistId": 418,
    "surname": "Patrick",
    "name": "Robert",
    "DOB": "1958-01-01T00:00:00.000Z"
  },
  {
    "artistId": 478,
    "surname": "Bell",
    "name": "Jamie",
    "DOB": "1986-01-01T00:00:00.000Z"
  },
  {
    "artistId": 488,
    "surname": "Spielberg",
    "name": "Steven",
    "DOB": "1946-01-01T00:00:00.000Z"
  },
  {
    "artistId": 500,
    "surname": "Cruise",
    "name": "Tom",
    "DOB": "1962-01-01T00:00:00.000Z"
  },
  {
    "artistId": 501,
    "surname": "Fanning",
    "name": "Dakota",
    "DOB": "1994-01-01T00:00:00.000Z"
  },
  {
    "artistId": 502,
    "surname": "Otto",
    "name": "Miranda",
    "DOB": "1967-01-01T00:00:00.000Z"
  },
  {
    "artistId": 503,
    "surname": "Chatwin",
    "name": "Justin",
    "DOB": "1982-01-01T00:00:00.000Z"
  },
  {
    "artistId": 504,
    "surname": "Robbins",
    "name": "Tim",
    "DOB": "1958-01-01T00:00:00.000Z"
  },
  {
    "artistId": 510,
    "surname": "Burton",
    "name": "Tim",
    "DOB": "1958-01-01T00:00:00.000Z"
  },
  {
    "artistId": 514,
    "surname": "Nicholson",
    "name": "Jack",
    "DOB": "1937-01-01T00:00:00.000Z"
  },
  {
    "artistId": 515,
    "surname": "Close",
    "name": "Glenn",
    "DOB": "1947-01-01T00:00:00.000Z"
  },
  {
    "artistId": 516,
    "surname": "Bening",
    "name": "Annette",
    "DOB": "1958-01-01T00:00:00.000Z"
  },
  {
    "artistId": 517,
    "surname": "Brosnan",
    "name": "Pierce",
    "DOB": "1953-01-01T00:00:00.000Z"
  },
  {
    "artistId": 518,
    "surname": "DeVito",
    "name": "Danny",
    "DOB": "1944-01-01T00:00:00.000Z"
  },
  {
    "artistId": 519,
    "surname": "Short",
    "name": "Martin",
    "DOB": "1950-01-01T00:00:00.000Z"
  },
  {
    "artistId": 520,
    "surname": "Jessica Parker",
    "name": "Sarah",
    "DOB": "1965-01-01T00:00:00.000Z"
  },
  {
    "artistId": 521,
    "surname": "J. Fox",
    "name": "Michael",
    "DOB": "1961-01-01T00:00:00.000Z"
  },
  {
    "artistId": 522,
    "surname": "Steiger",
    "name": "Rod",
    "DOB": "1925-01-01T00:00:00.000Z"
  },
  {
    "artistId": 524,
    "surname": "Portman",
    "name": "Natalie",
    "DOB": "1981-01-01T00:00:00.000Z"
  },
  {
    "artistId": 525,
    "surname": "Nolan",
    "name": "Christopher",
    "DOB": "1970-01-01T00:00:00.000Z"
  },
  {
    "artistId": 526,
    "surname": "Haas",
    "name": "Lukas",
    "DOB": "1976-01-01T00:00:00.000Z"
  },
  {
    "artistId": 529,
    "surname": "Pearce",
    "name": "Guy",
    "DOB": "1967-01-01T00:00:00.000Z"
  },
  {
    "artistId": 530,
    "surname": "Moss",
    "name": "Carrie-Anne",
    "DOB": "1967-01-01T00:00:00.000Z"
  },
  {
    "artistId": 532,
    "surname": "Pantoliano",
    "name": "Joe",
    "DOB": "1951-01-01T00:00:00.000Z"
  },
  {
    "artistId": 534,
    "surname": "Boone Junior",
    "name": "Mark",
    "DOB": "1955-01-01T00:00:00.000Z"
  },
  {
    "artistId": 535,
    "surname": "Fega",
    "name": "Russ",
    "DOB": null
  },
  {
    "artistId": 536,
    "surname": "Fox",
    "name": "Jorja",
    "DOB": "1968-01-01T00:00:00.000Z"
  },
  {
    "artistId": 537,
    "surname": "Tobolowsky",
    "name": "Stephen",
    "DOB": "1951-01-01T00:00:00.000Z"
  },
  {
    "artistId": 578,
    "surname": "Scott",
    "name": "Ridley",
    "DOB": "1937-01-01T00:00:00.000Z"
  },
  {
    "artistId": 585,
    "surname": "Hauer",
    "name": "Rutger",
    "DOB": "1944-01-01T00:00:00.000Z"
  },
  {
    "artistId": 586,
    "surname": "Young",
    "name": "Sean",
    "DOB": "1959-01-01T00:00:00.000Z"
  },
  {
    "artistId": 587,
    "surname": "James Olmos",
    "name": "Edward",
    "DOB": "1947-01-01T00:00:00.000Z"
  },
  {
    "artistId": 588,
    "surname": "Emmet Walsh",
    "name": "M.",
    "DOB": "1935-01-01T00:00:00.000Z"
  },
  {
    "artistId": 589,
    "surname": "Hannah",
    "name": "Daryl",
    "DOB": "1960-01-01T00:00:00.000Z"
  },
  {
    "artistId": 638,
    "surname": "Mann",
    "name": "Michael",
    "DOB": "1943-01-01T00:00:00.000Z"
  },
  {
    "artistId": 650,
    "surname": "Allen",
    "name": "Karen",
    "DOB": "1951-01-01T00:00:00.000Z"
  },
  {
    "artistId": 652,
    "surname": "Freeman",
    "name": "Paul",
    "DOB": "1943-01-01T00:00:00.000Z"
  },
  {
    "artistId": 653,
    "surname": "Lacey",
    "name": "Ronald",
    "DOB": "1935-01-01T00:00:00.000Z"
  },
  {
    "artistId": 655,
    "surname": "Rhys-Davies",
    "name": "John",
    "DOB": "1944-01-01T00:00:00.000Z"
  },
  {
    "artistId": 656,
    "surname": "Elliott",
    "name": "Denholm",
    "DOB": "1922-01-01T00:00:00.000Z"
  },
  {
    "artistId": 658,
    "surname": "Molina",
    "name": "Alfred",
    "DOB": "1953-01-01T00:00:00.000Z"
  },
  {
    "artistId": 659,
    "surname": "Kahler",
    "name": "Wolf",
    "DOB": "1940-01-01T00:00:00.000Z"
  },
  {
    "artistId": 660,
    "surname": "Higgins",
    "name": "Anthony",
    "DOB": "1947-01-01T00:00:00.000Z"
  },
  {
    "artistId": 678,
    "surname": "Gedeck",
    "name": "Martina",
    "DOB": "1961-01-01T00:00:00.000Z"
  },
  {
    "artistId": 689,
    "surname": "Capshaw",
    "name": "Kate",
    "DOB": "1953-01-01T00:00:00.000Z"
  },
  {
    "artistId": 690,
    "surname": "Huy Quan",
    "name": "Ke",
    "DOB": "1971-01-01T00:00:00.000Z"
  },
  {
    "artistId": 691,
    "surname": "Puri",
    "name": "Amrish",
    "DOB": "1932-01-01T00:00:00.000Z"
  },
  {
    "artistId": 693,
    "surname": "Seth",
    "name": "Roshan",
    "DOB": "1942-01-01T00:00:00.000Z"
  },
  {
    "artistId": 694,
    "surname": "Stone",
    "name": "Philip",
    "DOB": "1924-01-01T00:00:00.000Z"
  },
  {
    "artistId": 695,
    "surname": "Chiao",
    "name": "Roy",
    "DOB": "1927-01-01T00:00:00.000Z"
  },
  {
    "artistId": 738,
    "surname": "Connery",
    "name": "Sean",
    "DOB": "1930-01-01T00:00:00.000Z"
  },
  {
    "artistId": 739,
    "surname": "Doody",
    "name": "Alison",
    "DOB": "1966-01-01T00:00:00.000Z"
  },
  {
    "artistId": 740,
    "surname": "Glover",
    "name": "Julian",
    "DOB": "1935-01-01T00:00:00.000Z"
  },
  {
    "artistId": 741,
    "surname": "Phoenix",
    "name": "River",
    "DOB": "1970-01-01T00:00:00.000Z"
  },
  {
    "artistId": 780,
    "surname": "Cox",
    "name": "Ronny",
    "DOB": "1938-01-01T00:00:00.000Z"
  },
  {
    "artistId": 793,
    "surname": "Buñuel",
    "name": "Luis",
    "DOB": "1900-01-01T00:00:00.000Z"
  },
  {
    "artistId": 819,
    "surname": "Norton",
    "name": "Edward",
    "DOB": "1969-01-01T00:00:00.000Z"
  },
  {
    "artistId": 820,
    "surname": "Furlong",
    "name": "Edward",
    "DOB": "1977-01-01T00:00:00.000Z"
  },
  {
    "artistId": 854,
    "surname": "Stewart",
    "name": "James",
    "DOB": "1908-01-01T00:00:00.000Z"
  },
  {
    "artistId": 856,
    "surname": "Gazzara",
    "name": "Ben",
    "DOB": "1930-01-01T00:00:00.000Z"
  },
  {
    "artistId": 880,
    "surname": "Affleck",
    "name": "Ben",
    "DOB": "1972-01-01T00:00:00.000Z"
  },
  {
    "artistId": 882,
    "surname": "Tyler",
    "name": "Liv",
    "DOB": "1977-01-01T00:00:00.000Z"
  },
  {
    "artistId": 884,
    "surname": "Buscemi",
    "name": "Steve",
    "DOB": "1957-01-01T00:00:00.000Z"
  },
  {
    "artistId": 887,
    "surname": "Wilson",
    "name": "Owen",
    "DOB": "1968-01-01T00:00:00.000Z"
  },
  {
    "artistId": 920,
    "surname": "Prochnow",
    "name": "Jürgen",
    "DOB": "1941-01-01T00:00:00.000Z"
  },
  {
    "artistId": 922,
    "surname": "Garfield",
    "name": "Allen",
    "DOB": "1939-01-01T00:00:00.000Z"
  },
  {
    "artistId": 934,
    "surname": "Crowe",
    "name": "Russell",
    "DOB": "1964-01-01T00:00:00.000Z"
  },
  {
    "artistId": 935,
    "surname": "Nielsen",
    "name": "Connie",
    "DOB": "1965-01-01T00:00:00.000Z"
  },
  {
    "artistId": 936,
    "surname": "Reed",
    "name": "Oliver",
    "DOB": "1938-01-01T00:00:00.000Z"
  },
  {
    "artistId": 937,
    "surname": "Jacobi",
    "name": "Derek",
    "DOB": "1938-01-01T00:00:00.000Z"
  },
  {
    "artistId": 938,
    "surname": "Hounsou",
    "name": "Djimon",
    "DOB": "1964-01-01T00:00:00.000Z"
  },
  {
    "artistId": 1003,
    "surname": "Reno",
    "name": "Jean",
    "DOB": "1948-01-01T00:00:00.000Z"
  },
  {
    "artistId": 1019,
    "surname": "Mikkelsen",
    "name": "Mads",
    "DOB": "1965-01-01T00:00:00.000Z"
  },
  {
    "artistId": 1032,
    "surname": "Scorsese",
    "name": "Martin",
    "DOB": "1942-01-01T00:00:00.000Z"
  },
  {
    "artistId": 1036,
    "surname": "Shepherd",
    "name": "Cybill",
    "DOB": "1950-01-01T00:00:00.000Z"
  },
  {
    "artistId": 1037,
    "surname": "Keitel",
    "name": "Harvey",
    "DOB": "1939-01-01T00:00:00.000Z"
  },
  {
    "artistId": 1038,
    "surname": "Foster",
    "name": "Jodie",
    "DOB": "1962-01-01T00:00:00.000Z"
  },
  {
    "artistId": 1039,
    "surname": "Boyle",
    "name": "Peter",
    "DOB": "1935-01-01T00:00:00.000Z"
  },
  {
    "artistId": 1090,
    "surname": "McTiernan",
    "name": "John",
    "DOB": "1951-01-01T00:00:00.000Z"
  },
  {
    "artistId": 1100,
    "surname": "Schwarzenegger",
    "name": "Arnold",
    "DOB": "1947-01-01T00:00:00.000Z"
  },
  {
    "artistId": 1101,
    "surname": "Weathers",
    "name": "Carl",
    "DOB": "1948-01-01T00:00:00.000Z"
  },
  {
    "artistId": 1102,
    "surname": "Carrillo",
    "name": "Elpidia",
    "DOB": "1961-01-01T00:00:00.000Z"
  },
  {
    "artistId": 1103,
    "surname": "Duke",
    "name": "Bill",
    "DOB": "1943-01-01T00:00:00.000Z"
  },
  {
    "artistId": 1104,
    "surname": "Ventura",
    "name": "Jesse",
    "DOB": "1951-01-01T00:00:00.000Z"
  },
  {
    "artistId": 1105,
    "surname": "Landham",
    "name": "Sonny",
    "DOB": "1941-01-01T00:00:00.000Z"
  },
  {
    "artistId": 1106,
    "surname": "Chaves",
    "name": "Richard",
    "DOB": "1951-01-01T00:00:00.000Z"
  },
  {
    "artistId": 1118,
    "surname": "Šerbedžija",
    "name": "Rade",
    "DOB": "1946-01-01T00:00:00.000Z"
  },
  {
    "artistId": 1121,
    "surname": "del Toro",
    "name": "Benicio",
    "DOB": "1967-01-01T00:00:00.000Z"
  },
  {
    "artistId": 1141,
    "surname": "Vincent",
    "name": "Hélène",
    "DOB": "1943-01-01T00:00:00.000Z"
  },
  {
    "artistId": 1150,
    "surname": "De Palma",
    "name": "Brian",
    "DOB": "1940-01-01T00:00:00.000Z"
  },
  {
    "artistId": 1158,
    "surname": "Pacino",
    "name": "Al",
    "DOB": "1940-01-01T00:00:00.000Z"
  },
  {
    "artistId": 1164,
    "surname": "Murray Abraham",
    "name": "F.",
    "DOB": "1939-01-01T00:00:00.000Z"
  },
  {
    "artistId": 1204,
    "surname": "Roberts",
    "name": "Julia",
    "DOB": "1967-01-01T00:00:00.000Z"
  },
  {
    "artistId": 1205,
    "surname": "Gere",
    "name": "Richard",
    "DOB": "1949-01-01T00:00:00.000Z"
  },
  {
    "artistId": 1223,
    "surname": "Coen",
    "name": "Joel",
    "DOB": "1954-01-01T00:00:00.000Z"
  },
  {
    "artistId": 1224,
    "surname": "Coen",
    "name": "Ethan",
    "DOB": "1957-01-01T00:00:00.000Z"
  },
  {
    "artistId": 1229,
    "surname": "Bridges",
    "name": "Jeff",
    "DOB": "1949-01-01T00:00:00.000Z"
  },
  {
    "artistId": 1230,
    "surname": "Goodman",
    "name": "John",
    "DOB": "1952-01-01T00:00:00.000Z"
  },
  {
    "artistId": 1231,
    "surname": "Moore",
    "name": "Julianne",
    "DOB": "1960-01-01T00:00:00.000Z"
  },
  {
    "artistId": 1232,
    "surname": "Huddleston",
    "name": "David",
    "DOB": "1930-01-01T00:00:00.000Z"
  },
  {
    "artistId": 1233,
    "surname": "Seymour Hoffman",
    "name": "Philip",
    "DOB": "1967-01-01T00:00:00.000Z"
  },
  {
    "artistId": 1234,
    "surname": "Reid",
    "name": "Tara",
    "DOB": "1975-01-01T00:00:00.000Z"
  },
  {
    "artistId": 1235,
    "surname": "Moon",
    "name": "Philip",
    "DOB": null
  },
  {
    "artistId": 1236,
    "surname": "Pellegrino",
    "name": "Mark",
    "DOB": "1965-01-01T00:00:00.000Z"
  },
  {
    "artistId": 1243,
    "surname": "Allen",
    "name": "Woody",
    "DOB": "1935-01-01T00:00:00.000Z"
  },
  {
    "artistId": 1244,
    "surname": "Rhys Meyers",
    "name": "Jonathan",
    "DOB": "1977-01-01T00:00:00.000Z"
  },
  {
    "artistId": 1245,
    "surname": "Johansson",
    "name": "Scarlett",
    "DOB": "1984-01-01T00:00:00.000Z"
  },
  {
    "artistId": 1246,
    "surname": "Mortimer",
    "name": "Emily",
    "DOB": "1971-01-01T00:00:00.000Z"
  },
  {
    "artistId": 1248,
    "surname": "Cox",
    "name": "Brian",
    "DOB": "1946-01-01T00:00:00.000Z"
  },
  {
    "artistId": 1249,
    "surname": "Wilton",
    "name": "Penelope",
    "DOB": "1946-01-01T00:00:00.000Z"
  },
  {
    "artistId": 1270,
    "surname": "Martin Smith",
    "name": "Charles",
    "DOB": "1953-01-01T00:00:00.000Z"
  },
  {
    "artistId": 1271,
    "surname": "García",
    "name": "Andy",
    "DOB": "1956-01-01T00:00:00.000Z"
  },
  {
    "artistId": 1283,
    "surname": "Bonham Carter",
    "name": "Helena",
    "DOB": "1966-01-01T00:00:00.000Z"
  },
  {
    "artistId": 1327,
    "surname": "MCKellen",
    "name": "Ian",
    "DOB": "1939-01-01T00:00:00.000Z"
  },
  {
    "artistId": 1328,
    "surname": "Astin",
    "name": "Sean",
    "DOB": "1971-01-01T00:00:00.000Z"
  },
  {
    "artistId": 1329,
    "surname": "Boyd",
    "name": "Billy",
    "DOB": "1968-01-01T00:00:00.000Z"
  },
  {
    "artistId": 1330,
    "surname": "Monaghan",
    "name": "Dominic",
    "DOB": "1976-01-01T00:00:00.000Z"
  },
  {
    "artistId": 1331,
    "surname": "Weaving",
    "name": "Hugo",
    "DOB": "1960-01-01T00:00:00.000Z"
  },
  {
    "artistId": 1333,
    "surname": "Serkis",
    "name": "Andy",
    "DOB": "1964-01-01T00:00:00.000Z"
  },
  {
    "artistId": 1337,
    "surname": "Leung Chiu-wai",
    "name": "Tony",
    "DOB": "1962-01-01T00:00:00.000Z"
  },
  {
    "artistId": 1338,
    "surname": "Cheung",
    "name": "Maggie",
    "DOB": "1964-01-01T00:00:00.000Z"
  },
  {
    "artistId": 1339,
    "surname": "Ziyi",
    "name": "Zhang",
    "DOB": "1979-01-01T00:00:00.000Z"
  },
  {
    "artistId": 1341,
    "surname": "Yen",
    "name": "Donnie",
    "DOB": "1963-01-01T00:00:00.000Z"
  },
  {
    "artistId": 1369,
    "surname": "Hill",
    "name": "Bernard",
    "DOB": "1944-01-01T00:00:00.000Z"
  },
  {
    "artistId": 1370,
    "surname": "Dourif",
    "name": "Brad",
    "DOB": "1950-01-01T00:00:00.000Z"
  },
  {
    "artistId": 1466,
    "surname": "Durning",
    "name": "Charles",
    "DOB": "1923-01-01T00:00:00.000Z"
  },
  {
    "artistId": 1472,
    "surname": "McKinnon",
    "name": "Ray",
    "DOB": "1957-01-01T00:00:00.000Z"
  },
  {
    "artistId": 1524,
    "surname": "Ramis",
    "name": "Harold",
    "DOB": "1944-01-01T00:00:00.000Z"
  },
  {
    "artistId": 1532,
    "surname": "Murray",
    "name": "Bill",
    "DOB": "1950-01-01T00:00:00.000Z"
  },
  {
    "artistId": 1533,
    "surname": "MacDowell",
    "name": "Andie",
    "DOB": "1958-01-01T00:00:00.000Z"
  },
  {
    "artistId": 1534,
    "surname": "Elliott",
    "name": "Chris",
    "DOB": "1960-01-01T00:00:00.000Z"
  },
  {
    "artistId": 1535,
    "surname": "Doyle-Murray",
    "name": "Brian",
    "DOB": "1945-01-01T00:00:00.000Z"
  }
]